nomad_camels_driver_thorlabs_MFF/__init__.py
nomad_camels_driver_thorlabs_MFF/thorlabs_MFF.py
nomad_camels_driver_thorlabs_MFF/thorlabs_MFF_ophyd.py
nomad_camels_driver_thorlabs_MFF-0.1.0.dist-info/LICENSE.txt
nomad_camels_driver_thorlabs_MFF-0.1.0.dist-info/METADATA
nomad_camels_driver_thorlabs_MFF-0.1.0.dist-info/WHEEL
nomad_camels_driver_thorlabs_MFF-0.1.0.dist-info/top_level.txt
nomad_camels_driver_thorlabs_MFF-0.1.0.dist-info/RECORD
